[
  {
    "key": "BV1oHNc6yENA-8",
    "level": "IELTS 5.5",
    "topic": "Joining A New Team",
    "title": "【BBC六分钟 | 英语精读自制】2025年+2026年1-6月合集 | 全新手绘课件版+重点词汇+信息图梳理 - 8、a vaccine for cancer",
    "source": "Bilibili",
    "url": "https://www.bilibili.com/video/BV1oHNc6yENA?p=8",
    "embedUrl": "https://player.bilibili.com/player.html?bvid=BV1oHNc6yENA&page=8&autoplay=0",
    "bvid": "BV1oHNc6yENA",
    "cid": 39851133380,
    "page": 8,
    "playerType": "bilibili",
    "duration": "6:17",
    "durationSeconds": 377,
    "difficulty": "B1+ / IELTS 5.5",
    "focus": "Joining A New Team",
    "keywords": [
      "joining a new team",
      "【BBC六分钟 | 英语精读自制】2025年+2026年1-6月合集 | 全新手绘课件版+重点词汇+信息图梳理",
      "BBC六分钟,英语口语,英语学习,英语听力,英语,BBC"
    ],
    "whySuitable": "Bilibili 可播放候选；如含外挂字幕，可直接生成逐句精听课程。",
    "transcriptSource": "unavailable",
    "transcriptSegments": [],
    "id": "ielts-5-5-01"
  },
  {
    "key": "BV127411n7nj-11",
    "level": "IELTS 5.5",
    "topic": "Joining A New Team",
    "title": "【中英双语字幕】BBC官方音标教程 英式英语发音零基础教学 标准英语发音课程 英式英语音标分段讲解 英音英伦腔口语养成 - 9.短元音schwa[ə]",
    "source": "Bilibili",
    "url": "https://www.bilibili.com/video/BV127411n7nj?p=11",
    "embedUrl": "https://player.bilibili.com/player.html?bvid=BV127411n7nj&page=11&autoplay=0",
    "bvid": "BV127411n7nj",
    "cid": 169849847,
    "page": 11,
    "playerType": "bilibili",
    "duration": "4:11",
    "durationSeconds": 251,
    "difficulty": "B1+ / IELTS 5.5",
    "focus": "Joining A New Team",
    "keywords": [
      "joining a new team",
      "【中英双语字幕】BBC官方音标教程 英式英语发音零基础教学 标准英语发音课程 英式英语音标分段讲解 英音英伦腔口语养成",
      "英语学习,BBC,学习,听力,口语,英语,教育,课程,雅思,音标"
    ],
    "whySuitable": "Bilibili 可播放候选；如含外挂字幕，可直接生成逐句精听课程。",
    "transcriptSource": "unavailable",
    "transcriptSegments": [],
    "id": "ielts-5-5-02"
  },
  {
    "key": "BV1UbyZB9ERb-1",
    "level": "IELTS 5.5",
    "topic": "Polite Requests",
    "title": "【TED演讲】必看100场TED演讲合集 | 口语听力提升必备素材 | 双语字幕+精读笔记+重难点标注 - 【TED演讲】人生不只是要快乐",
    "source": "Bilibili",
    "url": "https://www.bilibili.com/video/BV1UbyZB9ERb",
    "embedUrl": "https://player.bilibili.com/player.html?bvid=BV1UbyZB9ERb&page=1&autoplay=0",
    "bvid": "BV1UbyZB9ERb",
    "cid": 33622133700,
    "page": 1,
    "playerType": "bilibili",
    "duration": "12:09",
    "durationSeconds": 729,
    "difficulty": "B1+ / IELTS 5.5",
    "focus": "Polite Requests",
    "keywords": [
      "polite requests",
      "【TED演讲】必看100场TED演讲合集 | 口语听力提升必备素材 | 双语字幕+精读笔记+重难点标注",
      "英语口语,TED,英语学习,英语听力"
    ],
    "whySuitable": "Bilibili 可播放候选；如含外挂字幕，可直接生成逐句精听课程。",
    "transcriptSource": "unavailable",
    "transcriptSegments": [],
    "id": "ielts-5-5-03"
  },
  {
    "key": "BV1zx41137yd-1",
    "level": "IELTS 5.5",
    "topic": "Joining A New Team",
    "title": "Conservative RP英音和BBC英音的区别 Best posh accent R.P. BBC English or Standard English",
    "source": "Bilibili",
    "url": "https://www.bilibili.com/video/BV1zx41137yd",
    "embedUrl": "https://player.bilibili.com/player.html?bvid=BV1zx41137yd&page=1&autoplay=0",
    "bvid": "BV1zx41137yd",
    "cid": 24640802,
    "page": 1,
    "playerType": "bilibili",
    "duration": "9:18",
    "durationSeconds": 558,
    "difficulty": "B1+ / IELTS 5.5",
    "focus": "Joining A New Team",
    "keywords": [
      "joining a new team",
      "Conservative RP英音和BBC英音的区别 Best posh accent R.P. BBC English or Standard English",
      "Jade Joddle,英国,英语学习,Posh English,英语,British English,RP English,BBC English"
    ],
    "whySuitable": "Bilibili 可播放候选；如含外挂字幕，可直接生成逐句精听课程。",
    "transcriptSource": "unavailable",
    "transcriptSegments": [],
    "id": "ielts-5-5-04"
  },
  {
    "key": "BV1oHNc6yENA-1",
    "level": "IELTS 5.5",
    "topic": "Joining A New Team",
    "title": "【BBC六分钟 | 英语精读自制】2025年+2026年1-6月合集 | 全新手绘课件版+重点词汇+信息图梳理 - 1、Are You Drinking Enough Water？",
    "source": "Bilibili",
    "url": "https://www.bilibili.com/video/BV1oHNc6yENA",
    "embedUrl": "https://player.bilibili.com/player.html?bvid=BV1oHNc6yENA&page=1&autoplay=0",
    "bvid": "BV1oHNc6yENA",
    "cid": 39949632041,
    "page": 1,
    "playerType": "bilibili",
    "duration": "6:19",
    "durationSeconds": 379,
    "difficulty": "B1+ / IELTS 5.5",
    "focus": "Joining A New Team",
    "keywords": [
      "joining a new team",
      "【BBC六分钟 | 英语精读自制】2025年+2026年1-6月合集 | 全新手绘课件版+重点词汇+信息图梳理",
      "BBC六分钟,英语口语,英语学习,英语听力,英语,BBC"
    ],
    "whySuitable": "Bilibili 可播放候选；如含外挂字幕，可直接生成逐句精听课程。",
    "transcriptSource": "unavailable",
    "transcriptSegments": [],
    "id": "ielts-5-5-05"
  },
  {
    "key": "BV1oHNc6yENA-2",
    "level": "IELTS 5.5",
    "topic": "Joining A New Team",
    "title": "【BBC六分钟 | 英语精读自制】2025年+2026年1-6月合集 | 全新手绘课件版+重点词汇+信息图梳理 - 2、eating 50 year old stew",
    "source": "Bilibili",
    "url": "https://www.bilibili.com/video/BV1oHNc6yENA?p=2",
    "embedUrl": "https://player.bilibili.com/player.html?bvid=BV1oHNc6yENA&page=2&autoplay=0",
    "bvid": "BV1oHNc6yENA",
    "cid": 39850869607,
    "page": 2,
    "playerType": "bilibili",
    "duration": "6:15",
    "durationSeconds": 375,
    "difficulty": "B1+ / IELTS 5.5",
    "focus": "Joining A New Team",
    "keywords": [
      "joining a new team",
      "【BBC六分钟 | 英语精读自制】2025年+2026年1-6月合集 | 全新手绘课件版+重点词汇+信息图梳理",
      "BBC六分钟,英语口语,英语学习,英语听力,英语,BBC"
    ],
    "whySuitable": "Bilibili 可播放候选；如含外挂字幕，可直接生成逐句精听课程。",
    "transcriptSource": "unavailable",
    "transcriptSegments": [],
    "id": "ielts-5-5-06"
  },
  {
    "key": "BV1oHNc6yENA-3",
    "level": "IELTS 5.5",
    "topic": "Joining A New Team",
    "title": "【BBC六分钟 | 英语精读自制】2025年+2026年1-6月合集 | 全新手绘课件版+重点词汇+信息图梳理 - 3、how the world learned to love fast food",
    "source": "Bilibili",
    "url": "https://www.bilibili.com/video/BV1oHNc6yENA?p=3",
    "embedUrl": "https://player.bilibili.com/player.html?bvid=BV1oHNc6yENA&page=3&autoplay=0",
    "bvid": "BV1oHNc6yENA",
    "cid": 39850871708,
    "page": 3,
    "playerType": "bilibili",
    "duration": "6:18",
    "durationSeconds": 378,
    "difficulty": "B1+ / IELTS 5.5",
    "focus": "Joining A New Team",
    "keywords": [
      "joining a new team",
      "【BBC六分钟 | 英语精读自制】2025年+2026年1-6月合集 | 全新手绘课件版+重点词汇+信息图梳理",
      "BBC六分钟,英语口语,英语学习,英语听力,英语,BBC"
    ],
    "whySuitable": "Bilibili 可播放候选；如含外挂字幕，可直接生成逐句精听课程。",
    "transcriptSource": "unavailable",
    "transcriptSegments": [],
    "id": "ielts-5-5-07"
  },
  {
    "key": "BV1oHNc6yENA-4",
    "level": "IELTS 5.5",
    "topic": "Joining A New Team",
    "title": "【BBC六分钟 | 英语精读自制】2025年+2026年1-6月合集 | 全新手绘课件版+重点词汇+信息图梳理 - 4、becoming a musician",
    "source": "Bilibili",
    "url": "https://www.bilibili.com/video/BV1oHNc6yENA?p=4",
    "embedUrl": "https://player.bilibili.com/player.html?bvid=BV1oHNc6yENA&page=4&autoplay=0",
    "bvid": "BV1oHNc6yENA",
    "cid": 39850936643,
    "page": 4,
    "playerType": "bilibili",
    "duration": "6:28",
    "durationSeconds": 388,
    "difficulty": "B1+ / IELTS 5.5",
    "focus": "Joining A New Team",
    "keywords": [
      "joining a new team",
      "【BBC六分钟 | 英语精读自制】2025年+2026年1-6月合集 | 全新手绘课件版+重点词汇+信息图梳理",
      "BBC六分钟,英语口语,英语学习,英语听力,英语,BBC"
    ],
    "whySuitable": "Bilibili 可播放候选；如含外挂字幕，可直接生成逐句精听课程。",
    "transcriptSource": "unavailable",
    "transcriptSegments": [],
    "id": "ielts-5-5-08"
  },
  {
    "key": "BV1oHNc6yENA-5",
    "level": "IELTS 5.5",
    "topic": "Joining A New Team",
    "title": "【BBC六分钟 | 英语精读自制】2025年+2026年1-6月合集 | 全新手绘课件版+重点词汇+信息图梳理 - 5、why smells make us feel at home",
    "source": "Bilibili",
    "url": "https://www.bilibili.com/video/BV1oHNc6yENA?p=5",
    "embedUrl": "https://player.bilibili.com/player.html?bvid=BV1oHNc6yENA&page=5&autoplay=0",
    "bvid": "BV1oHNc6yENA",
    "cid": 39851001056,
    "page": 5,
    "playerType": "bilibili",
    "duration": "6:18",
    "durationSeconds": 378,
    "difficulty": "B1+ / IELTS 5.5",
    "focus": "Joining A New Team",
    "keywords": [
      "joining a new team",
      "【BBC六分钟 | 英语精读自制】2025年+2026年1-6月合集 | 全新手绘课件版+重点词汇+信息图梳理",
      "BBC六分钟,英语口语,英语学习,英语听力,英语,BBC"
    ],
    "whySuitable": "Bilibili 可播放候选；如含外挂字幕，可直接生成逐句精听课程。",
    "transcriptSource": "unavailable",
    "transcriptSegments": [],
    "id": "ielts-5-5-09"
  },
  {
    "key": "BV1oHNc6yENA-6",
    "level": "IELTS 5.5",
    "topic": "Joining A New Team",
    "title": "【BBC六分钟 | 英语精读自制】2025年+2026年1-6月合集 | 全新手绘课件版+重点词汇+信息图梳理 - 6、rage bait",
    "source": "Bilibili",
    "url": "https://www.bilibili.com/video/BV1oHNc6yENA?p=6",
    "embedUrl": "https://player.bilibili.com/player.html?bvid=BV1oHNc6yENA&page=6&autoplay=0",
    "bvid": "BV1oHNc6yENA",
    "cid": 39851065348,
    "page": 6,
    "playerType": "bilibili",
    "duration": "6:15",
    "durationSeconds": 375,
    "difficulty": "B1+ / IELTS 5.5",
    "focus": "Joining A New Team",
    "keywords": [
      "joining a new team",
      "【BBC六分钟 | 英语精读自制】2025年+2026年1-6月合集 | 全新手绘课件版+重点词汇+信息图梳理",
      "BBC六分钟,英语口语,英语学习,英语听力,英语,BBC"
    ],
    "whySuitable": "Bilibili 可播放候选；如含外挂字幕，可直接生成逐句精听课程。",
    "transcriptSource": "unavailable",
    "transcriptSegments": [],
    "id": "ielts-5-5-10"
  },
  {
    "key": "BV1oHNc6yENA-7",
    "level": "IELTS 5.5",
    "topic": "Joining A New Team",
    "title": "【BBC六分钟 | 英语精读自制】2025年+2026年1-6月合集 | 全新手绘课件版+重点词汇+信息图梳理 - 7、young women on social media",
    "source": "Bilibili",
    "url": "https://www.bilibili.com/video/BV1oHNc6yENA?p=7",
    "embedUrl": "https://player.bilibili.com/player.html?bvid=BV1oHNc6yENA&page=7&autoplay=0",
    "bvid": "BV1oHNc6yENA",
    "cid": 39851069287,
    "page": 7,
    "playerType": "bilibili",
    "duration": "6:15",
    "durationSeconds": 375,
    "difficulty": "B1+ / IELTS 5.5",
    "focus": "Joining A New Team",
    "keywords": [
      "joining a new team",
      "【BBC六分钟 | 英语精读自制】2025年+2026年1-6月合集 | 全新手绘课件版+重点词汇+信息图梳理",
      "BBC六分钟,英语口语,英语学习,英语听力,英语,BBC"
    ],
    "whySuitable": "Bilibili 可播放候选；如含外挂字幕，可直接生成逐句精听课程。",
    "transcriptSource": "unavailable",
    "transcriptSegments": [],
    "id": "ielts-5-5-11"
  },
  {
    "key": "BV1oHNc6yENA-9",
    "level": "IELTS 5.5",
    "topic": "Joining A New Team",
    "title": "【BBC六分钟 | 英语精读自制】2025年+2026年1-6月合集 | 全新手绘课件版+重点词汇+信息图梳理 - 9、the country that measures happiness",
    "source": "Bilibili",
    "url": "https://www.bilibili.com/video/BV1oHNc6yENA?p=9",
    "embedUrl": "https://player.bilibili.com/player.html?bvid=BV1oHNc6yENA&page=9&autoplay=0",
    "bvid": "BV1oHNc6yENA",
    "cid": 39851197259,
    "page": 9,
    "playerType": "bilibili",
    "duration": "6:14",
    "durationSeconds": 374,
    "difficulty": "B1+ / IELTS 5.5",
    "focus": "Joining A New Team",
    "keywords": [
      "joining a new team",
      "【BBC六分钟 | 英语精读自制】2025年+2026年1-6月合集 | 全新手绘课件版+重点词汇+信息图梳理",
      "BBC六分钟,英语口语,英语学习,英语听力,英语,BBC"
    ],
    "whySuitable": "Bilibili 可播放候选；如含外挂字幕，可直接生成逐句精听课程。",
    "transcriptSource": "unavailable",
    "transcriptSegments": [],
    "id": "ielts-5-5-12"
  },
  {
    "key": "BV1oHNc6yENA-10",
    "level": "IELTS 5.5",
    "topic": "Joining A New Team",
    "title": "【BBC六分钟 | 英语精读自制】2025年+2026年1-6月合集 | 全新手绘课件版+重点词汇+信息图梳理 - 10、should we eat less rice",
    "source": "Bilibili",
    "url": "https://www.bilibili.com/video/BV1oHNc6yENA?p=10",
    "embedUrl": "https://player.bilibili.com/player.html?bvid=BV1oHNc6yENA&page=10&autoplay=0",
    "bvid": "BV1oHNc6yENA",
    "cid": 39851199573,
    "page": 10,
    "playerType": "bilibili",
    "duration": "6:15",
    "durationSeconds": 375,
    "difficulty": "B1+ / IELTS 5.5",
    "focus": "Joining A New Team",
    "keywords": [
      "joining a new team",
      "【BBC六分钟 | 英语精读自制】2025年+2026年1-6月合集 | 全新手绘课件版+重点词汇+信息图梳理",
      "BBC六分钟,英语口语,英语学习,英语听力,英语,BBC"
    ],
    "whySuitable": "Bilibili 可播放候选；如含外挂字幕，可直接生成逐句精听课程。",
    "transcriptSource": "unavailable",
    "transcriptSegments": [],
    "id": "ielts-5-5-13"
  },
  {
    "key": "BV1jYC6YREbg-1",
    "level": "IELTS 5.5",
    "topic": "Polite Requests",
    "title": "【BBC Learning English】【2024全集】6 Minute English - 2024-12-26 | Embarrassed to go to the doctor",
    "source": "Bilibili",
    "url": "https://www.bilibili.com/video/BV1jYC6YREbg",
    "embedUrl": "https://player.bilibili.com/player.html?bvid=BV1jYC6YREbg&page=1&autoplay=0",
    "bvid": "BV1jYC6YREbg",
    "cid": 27548060810,
    "page": 1,
    "playerType": "bilibili",
    "duration": "6:15",
    "durationSeconds": 375,
    "difficulty": "B1+ / IELTS 5.5",
    "focus": "Polite Requests",
    "keywords": [
      "polite requests",
      "【BBC Learning English】【2024全集】6 Minute English",
      "英语听力,播客,英式发音,雅思,英语学习,英文播客,英剧,英语"
    ],
    "whySuitable": "Bilibili 可播放候选；如含外挂字幕，可直接生成逐句精听课程。",
    "transcriptSource": "unavailable",
    "transcriptSegments": [],
    "id": "ielts-5-5-14"
  },
  {
    "key": "BV1jYC6YREbg-2",
    "level": "IELTS 5.5",
    "topic": "Polite Requests",
    "title": "【BBC Learning English】【2024全集】6 Minute English - 2024-12-19 | Call centres: Are you talking to AI",
    "source": "Bilibili",
    "url": "https://www.bilibili.com/video/BV1jYC6YREbg?p=2",
    "embedUrl": "https://player.bilibili.com/player.html?bvid=BV1jYC6YREbg&page=2&autoplay=0",
    "bvid": "BV1jYC6YREbg",
    "cid": 27548061096,
    "page": 2,
    "playerType": "bilibili",
    "duration": "6:15",
    "durationSeconds": 375,
    "difficulty": "B1+ / IELTS 5.5",
    "focus": "Polite Requests",
    "keywords": [
      "polite requests",
      "【BBC Learning English】【2024全集】6 Minute English",
      "英语听力,播客,英式发音,雅思,英语学习,英文播客,英剧,英语"
    ],
    "whySuitable": "Bilibili 可播放候选；如含外挂字幕，可直接生成逐句精听课程。",
    "transcriptSource": "unavailable",
    "transcriptSegments": [],
    "id": "ielts-5-5-15"
  },
  {
    "key": "BV1jYC6YREbg-3",
    "level": "IELTS 5.5",
    "topic": "Polite Requests",
    "title": "【BBC Learning English】【2024全集】6 Minute English - 2024-12-12 | Making 'mum friends'",
    "source": "Bilibili",
    "url": "https://www.bilibili.com/video/BV1jYC6YREbg?p=3",
    "embedUrl": "https://player.bilibili.com/player.html?bvid=BV1jYC6YREbg&page=3&autoplay=0",
    "bvid": "BV1jYC6YREbg",
    "cid": 27548061665,
    "page": 3,
    "playerType": "bilibili",
    "duration": "6:15",
    "durationSeconds": 375,
    "difficulty": "B1+ / IELTS 5.5",
    "focus": "Polite Requests",
    "keywords": [
      "polite requests",
      "【BBC Learning English】【2024全集】6 Minute English",
      "英语听力,播客,英式发音,雅思,英语学习,英文播客,英剧,英语"
    ],
    "whySuitable": "Bilibili 可播放候选；如含外挂字幕，可直接生成逐句精听课程。",
    "transcriptSource": "unavailable",
    "transcriptSegments": [],
    "id": "ielts-5-5-16"
  },
  {
    "key": "BV1jYC6YREbg-4",
    "level": "IELTS 5.5",
    "topic": "Polite Requests",
    "title": "【BBC Learning English】【2024全集】6 Minute English - 2024-12-05 | Can you trust ancestry DNA kits",
    "source": "Bilibili",
    "url": "https://www.bilibili.com/video/BV1jYC6YREbg?p=4",
    "embedUrl": "https://player.bilibili.com/player.html?bvid=BV1jYC6YREbg&page=4&autoplay=0",
    "bvid": "BV1jYC6YREbg",
    "cid": 27548123430,
    "page": 4,
    "playerType": "bilibili",
    "duration": "6:15",
    "durationSeconds": 375,
    "difficulty": "B1+ / IELTS 5.5",
    "focus": "Polite Requests",
    "keywords": [
      "polite requests",
      "【BBC Learning English】【2024全集】6 Minute English",
      "英语听力,播客,英式发音,雅思,英语学习,英文播客,英剧,英语"
    ],
    "whySuitable": "Bilibili 可播放候选；如含外挂字幕，可直接生成逐句精听课程。",
    "transcriptSource": "unavailable",
    "transcriptSegments": [],
    "id": "ielts-5-5-17"
  },
  {
    "key": "BV1jYC6YREbg-5",
    "level": "IELTS 5.5",
    "topic": "Polite Requests",
    "title": "【BBC Learning English】【2024全集】6 Minute English - 2024-11-28 | How babies learn to talk",
    "source": "Bilibili",
    "url": "https://www.bilibili.com/video/BV1jYC6YREbg?p=5",
    "embedUrl": "https://player.bilibili.com/player.html?bvid=BV1jYC6YREbg&page=5&autoplay=0",
    "bvid": "BV1jYC6YREbg",
    "cid": 27548123947,
    "page": 5,
    "playerType": "bilibili",
    "duration": "6:15",
    "durationSeconds": 375,
    "difficulty": "B1+ / IELTS 5.5",
    "focus": "Polite Requests",
    "keywords": [
      "polite requests",
      "【BBC Learning English】【2024全集】6 Minute English",
      "英语听力,播客,英式发音,雅思,英语学习,英文播客,英剧,英语"
    ],
    "whySuitable": "Bilibili 可播放候选；如含外挂字幕，可直接生成逐句精听课程。",
    "transcriptSource": "unavailable",
    "transcriptSegments": [],
    "id": "ielts-5-5-18"
  },
  {
    "key": "BV1jYC6YREbg-6",
    "level": "IELTS 5.5",
    "topic": "Polite Requests",
    "title": "【BBC Learning English】【2024全集】6 Minute English - 2024-11-21 | The secrets to a healthy old age",
    "source": "Bilibili",
    "url": "https://www.bilibili.com/video/BV1jYC6YREbg?p=6",
    "embedUrl": "https://player.bilibili.com/player.html?bvid=BV1jYC6YREbg&page=6&autoplay=0",
    "bvid": "BV1jYC6YREbg",
    "cid": 27548124346,
    "page": 6,
    "playerType": "bilibili",
    "duration": "6:15",
    "durationSeconds": 375,
    "difficulty": "B1+ / IELTS 5.5",
    "focus": "Polite Requests",
    "keywords": [
      "polite requests",
      "【BBC Learning English】【2024全集】6 Minute English",
      "英语听力,播客,英式发音,雅思,英语学习,英文播客,英剧,英语"
    ],
    "whySuitable": "Bilibili 可播放候选；如含外挂字幕，可直接生成逐句精听课程。",
    "transcriptSource": "unavailable",
    "transcriptSegments": [],
    "id": "ielts-5-5-19"
  },
  {
    "key": "BV1jYC6YREbg-7",
    "level": "IELTS 5.5",
    "topic": "Polite Requests",
    "title": "【BBC Learning English】【2024全集】6 Minute English - 2024-11-14 | The bond between sisters",
    "source": "Bilibili",
    "url": "https://www.bilibili.com/video/BV1jYC6YREbg?p=7",
    "embedUrl": "https://player.bilibili.com/player.html?bvid=BV1jYC6YREbg&page=7&autoplay=0",
    "bvid": "BV1jYC6YREbg",
    "cid": 27548124734,
    "page": 7,
    "playerType": "bilibili",
    "duration": "6:13",
    "durationSeconds": 373,
    "difficulty": "B1+ / IELTS 5.5",
    "focus": "Polite Requests",
    "keywords": [
      "polite requests",
      "【BBC Learning English】【2024全集】6 Minute English",
      "英语听力,播客,英式发音,雅思,英语学习,英文播客,英剧,英语"
    ],
    "whySuitable": "Bilibili 可播放候选；如含外挂字幕，可直接生成逐句精听课程。",
    "transcriptSource": "unavailable",
    "transcriptSegments": [],
    "id": "ielts-5-5-20"
  },
  {
    "key": "BV1jYC6YREbg-8",
    "level": "IELTS 5.5",
    "topic": "Polite Requests",
    "title": "【BBC Learning English】【2024全集】6 Minute English - 2024-11-07 | Having acne",
    "source": "Bilibili",
    "url": "https://www.bilibili.com/video/BV1jYC6YREbg?p=8",
    "embedUrl": "https://player.bilibili.com/player.html?bvid=BV1jYC6YREbg&page=8&autoplay=0",
    "bvid": "BV1jYC6YREbg",
    "cid": 27548125224,
    "page": 8,
    "playerType": "bilibili",
    "duration": "6:13",
    "durationSeconds": 373,
    "difficulty": "B1+ / IELTS 5.5",
    "focus": "Polite Requests",
    "keywords": [
      "polite requests",
      "【BBC Learning English】【2024全集】6 Minute English",
      "英语听力,播客,英式发音,雅思,英语学习,英文播客,英剧,英语"
    ],
    "whySuitable": "Bilibili 可播放候选；如含外挂字幕，可直接生成逐句精听课程。",
    "transcriptSource": "unavailable",
    "transcriptSegments": [],
    "id": "ielts-5-5-21"
  },
  {
    "key": "BV1jYC6YREbg-9",
    "level": "IELTS 5.5",
    "topic": "Polite Requests",
    "title": "【BBC Learning English】【2024全集】6 Minute English - 2024-10-31 | Why you need a good night's sleep",
    "source": "Bilibili",
    "url": "https://www.bilibili.com/video/BV1jYC6YREbg?p=9",
    "embedUrl": "https://player.bilibili.com/player.html?bvid=BV1jYC6YREbg&page=9&autoplay=0",
    "bvid": "BV1jYC6YREbg",
    "cid": 27548125776,
    "page": 9,
    "playerType": "bilibili",
    "duration": "6:16",
    "durationSeconds": 376,
    "difficulty": "B1+ / IELTS 5.5",
    "focus": "Polite Requests",
    "keywords": [
      "polite requests",
      "【BBC Learning English】【2024全集】6 Minute English",
      "英语听力,播客,英式发音,雅思,英语学习,英文播客,英剧,英语"
    ],
    "whySuitable": "Bilibili 可播放候选；如含外挂字幕，可直接生成逐句精听课程。",
    "transcriptSource": "unavailable",
    "transcriptSegments": [],
    "id": "ielts-5-5-22"
  },
  {
    "key": "BV1jYC6YREbg-10",
    "level": "IELTS 5.5",
    "topic": "Polite Requests",
    "title": "【BBC Learning English】【2024全集】6 Minute English - 2024-10-24 | Divorce: Why does it happen",
    "source": "Bilibili",
    "url": "https://www.bilibili.com/video/BV1jYC6YREbg?p=10",
    "embedUrl": "https://player.bilibili.com/player.html?bvid=BV1jYC6YREbg&page=10&autoplay=0",
    "bvid": "BV1jYC6YREbg",
    "cid": 27548126208,
    "page": 10,
    "playerType": "bilibili",
    "duration": "6:14",
    "durationSeconds": 374,
    "difficulty": "B1+ / IELTS 5.5",
    "focus": "Polite Requests",
    "keywords": [
      "polite requests",
      "【BBC Learning English】【2024全集】6 Minute English",
      "英语听力,播客,英式发音,雅思,英语学习,英文播客,英剧,英语"
    ],
    "whySuitable": "Bilibili 可播放候选；如含外挂字幕，可直接生成逐句精听课程。",
    "transcriptSource": "unavailable",
    "transcriptSegments": [],
    "id": "ielts-5-5-23"
  },
  {
    "key": "BV1gVzzBsEAk-1",
    "level": "IELTS 5.5",
    "topic": "Polite Requests",
    "title": "BBC Learning English for Work 为工作学习英语 | BBC Learning English - Work emails Office English episode 1",
    "source": "Bilibili",
    "url": "https://www.bilibili.com/video/BV1gVzzBsEAk",
    "embedUrl": "https://player.bilibili.com/player.html?bvid=BV1gVzzBsEAk&page=1&autoplay=0",
    "bvid": "BV1gVzzBsEAk",
    "cid": 35576613612,
    "page": 1,
    "playerType": "bilibili",
    "duration": "12:59",
    "durationSeconds": 779,
    "difficulty": "B1+ / IELTS 5.5",
    "focus": "Polite Requests",
    "keywords": [
      "polite requests",
      "BBC Learning English for Work 为工作学习英语 | BBC Learning English",
      "课程,学习,英语"
    ],
    "whySuitable": "Bilibili 可播放候选；如含外挂字幕，可直接生成逐句精听课程。",
    "transcriptSource": "unavailable",
    "transcriptSegments": [],
    "id": "ielts-5-5-24"
  },
  {
    "key": "BV1gVzzBsEAk-2",
    "level": "IELTS 5.5",
    "topic": "Polite Requests",
    "title": "BBC Learning English for Work 为工作学习英语 | BBC Learning English - Meetings Office English episode 2",
    "source": "Bilibili",
    "url": "https://www.bilibili.com/video/BV1gVzzBsEAk?p=2",
    "embedUrl": "https://player.bilibili.com/player.html?bvid=BV1gVzzBsEAk&page=2&autoplay=0",
    "bvid": "BV1gVzzBsEAk",
    "cid": 35576614272,
    "page": 2,
    "playerType": "bilibili",
    "duration": "10:24",
    "durationSeconds": 624,
    "difficulty": "B1+ / IELTS 5.5",
    "focus": "Polite Requests",
    "keywords": [
      "polite requests",
      "BBC Learning English for Work 为工作学习英语 | BBC Learning English",
      "课程,学习,英语"
    ],
    "whySuitable": "Bilibili 可播放候选；如含外挂字幕，可直接生成逐句精听课程。",
    "transcriptSource": "unavailable",
    "transcriptSegments": [],
    "id": "ielts-5-5-25"
  },
  {
    "key": "BV1gVzzBsEAk-3",
    "level": "IELTS 5.5",
    "topic": "Polite Requests",
    "title": "BBC Learning English for Work 为工作学习英语 | BBC Learning English - Chasing people Office English episode 3",
    "source": "Bilibili",
    "url": "https://www.bilibili.com/video/BV1gVzzBsEAk?p=3",
    "embedUrl": "https://player.bilibili.com/player.html?bvid=BV1gVzzBsEAk&page=3&autoplay=0",
    "bvid": "BV1gVzzBsEAk",
    "cid": 35576614853,
    "page": 3,
    "playerType": "bilibili",
    "duration": "12:03",
    "durationSeconds": 723,
    "difficulty": "B1+ / IELTS 5.5",
    "focus": "Polite Requests",
    "keywords": [
      "polite requests",
      "BBC Learning English for Work 为工作学习英语 | BBC Learning English",
      "课程,学习,英语"
    ],
    "whySuitable": "Bilibili 可播放候选；如含外挂字幕，可直接生成逐句精听课程。",
    "transcriptSource": "unavailable",
    "transcriptSegments": [],
    "id": "ielts-5-5-26"
  },
  {
    "key": "BV1gVzzBsEAk-4",
    "level": "IELTS 5.5",
    "topic": "Polite Requests",
    "title": "BBC Learning English for Work 为工作学习英语 | BBC Learning English - Calls and instant messages Office English episode 4",
    "source": "Bilibili",
    "url": "https://www.bilibili.com/video/BV1gVzzBsEAk?p=4",
    "embedUrl": "https://player.bilibili.com/player.html?bvid=BV1gVzzBsEAk&page=4&autoplay=0",
    "bvid": "BV1gVzzBsEAk",
    "cid": 35576676576,
    "page": 4,
    "playerType": "bilibili",
    "duration": "11:24",
    "durationSeconds": 684,
    "difficulty": "B1+ / IELTS 5.5",
    "focus": "Polite Requests",
    "keywords": [
      "polite requests",
      "BBC Learning English for Work 为工作学习英语 | BBC Learning English",
      "课程,学习,英语"
    ],
    "whySuitable": "Bilibili 可播放候选；如含外挂字幕，可直接生成逐句精听课程。",
    "transcriptSource": "unavailable",
    "transcriptSegments": [],
    "id": "ielts-5-5-27"
  },
  {
    "key": "BV1rW411D7TW-1",
    "level": "IELTS 5.5",
    "topic": "Polite Requests",
    "title": "【英国/BBC】《Look Ahead》展望未来 （60集全）BBC English Learning - 01- International English",
    "source": "Bilibili",
    "url": "https://www.bilibili.com/video/BV1rW411D7TW",
    "embedUrl": "https://player.bilibili.com/player.html?bvid=BV1rW411D7TW&page=1&autoplay=0",
    "bvid": "BV1rW411D7TW",
    "cid": 52917087,
    "page": 1,
    "playerType": "bilibili",
    "duration": "12:23",
    "durationSeconds": 743,
    "difficulty": "B1+ / IELTS 5.5",
    "focus": "Polite Requests",
    "keywords": [
      "polite requests",
      "【英国/BBC】《Look Ahead》展望未来 （60集全）BBC English Learning",
      "语言,英语学习,英音,英语口语,英语,教育"
    ],
    "whySuitable": "Bilibili 可播放候选；如含外挂字幕，可直接生成逐句精听课程。",
    "transcriptSource": "unavailable",
    "transcriptSegments": [],
    "id": "ielts-5-5-28"
  },
  {
    "key": "BV1zy2eBVEgn-1",
    "level": "IELTS 5.5",
    "topic": "Polite Requests",
    "title": "全90集【Yakka Dee开口说英语】低幼英语启蒙神器1-7季--英国BBC动画片 - 3.Book",
    "source": "Bilibili",
    "url": "https://www.bilibili.com/video/BV1zy2eBVEgn",
    "embedUrl": "https://player.bilibili.com/player.html?bvid=BV1zy2eBVEgn&page=1&autoplay=0",
    "bvid": "BV1zy2eBVEgn",
    "cid": 34498350638,
    "page": 1,
    "playerType": "bilibili",
    "duration": "5:09",
    "durationSeconds": 309,
    "difficulty": "B1+ / IELTS 5.5",
    "focus": "Polite Requests",
    "keywords": [
      "polite requests",
      "全90集【Yakka Dee开口说英语】低幼英语启蒙神器1-7季--英国BBC动画片",
      "英文,开口说英语,英语启蒙,英语动画片,开口神器,英语学习,Yakka Dee,少儿英语,英国动画片,英语听力"
    ],
    "whySuitable": "Bilibili 可播放候选；如含外挂字幕，可直接生成逐句精听课程。",
    "transcriptSource": "unavailable",
    "transcriptSegments": [],
    "id": "ielts-5-5-29"
  },
  {
    "key": "BV1AE411V7qv-1",
    "level": "IELTS 5.5",
    "topic": "Polite Requests",
    "title": "BBC learning English BBC英语 Stories for children 儿童故事 - 尼尔的童话书",
    "source": "Bilibili",
    "url": "https://www.bilibili.com/video/BV1AE411V7qv",
    "embedUrl": "https://player.bilibili.com/player.html?bvid=BV1AE411V7qv&page=1&autoplay=0",
    "bvid": "BV1AE411V7qv",
    "cid": 174454988,
    "page": 1,
    "playerType": "bilibili",
    "duration": "7:14",
    "durationSeconds": 434,
    "difficulty": "B1+ / IELTS 5.5",
    "focus": "Polite Requests",
    "keywords": [
      "polite requests",
      "BBC learning English BBC英语 Stories for children 儿童故事",
      "少儿英语,英式英语,英语听力,英音,BBC,教育"
    ],
    "whySuitable": "Bilibili 可播放候选；如含外挂字幕，可直接生成逐句精听课程。",
    "transcriptSource": "unavailable",
    "transcriptSegments": [],
    "id": "ielts-5-5-30"
  },
  {
    "key": "BV1oSTEzjEMr-1",
    "level": "IELTS 5.5",
    "topic": "Polite Requests",
    "title": "【BBC 简单英语】11.谈论睡眠 Talking about sleep - 【BBC 简单英语】11.谈论睡眠 Talking about sleep",
    "source": "Bilibili",
    "url": "https://www.bilibili.com/video/BV1oSTEzjEMr",
    "embedUrl": "https://player.bilibili.com/player.html?bvid=BV1oSTEzjEMr&page=1&autoplay=0",
    "bvid": "BV1oSTEzjEMr",
    "cid": 30321282053,
    "page": 1,
    "playerType": "bilibili",
    "duration": "5:28",
    "durationSeconds": 328,
    "difficulty": "B1+ / IELTS 5.5",
    "focus": "Polite Requests",
    "keywords": [
      "polite requests",
      "【BBC 简单英语】11.谈论睡眠 Talking about sleep",
      "BBC,每日英语,英语听力,英语没那么难,英语口语,英语,流利说英语,口语,英语天天练,英语学习"
    ],
    "whySuitable": "Bilibili 可播放候选；如含外挂字幕，可直接生成逐句精听课程。",
    "transcriptSource": "unavailable",
    "transcriptSegments": [],
    "id": "ielts-5-5-31"
  },
  {
    "key": "BV1LheuzXEKr-1",
    "level": "IELTS 5.5",
    "topic": "Joining A New Team",
    "title": "全469节中英字幕【火爆油管外教英语】Vanessa English 覆盖语法+词汇+发音+学习方法四大板块 原汁原味学英语 - Vanessa-如何学习英语-01",
    "source": "Bilibili",
    "url": "https://www.bilibili.com/video/BV1LheuzXEKr",
    "embedUrl": "https://player.bilibili.com/player.html?bvid=BV1LheuzXEKr&page=1&autoplay=0",
    "bvid": "BV1LheuzXEKr",
    "cid": 31818321902,
    "page": 1,
    "playerType": "bilibili",
    "duration": "12:48",
    "durationSeconds": 768,
    "difficulty": "B1+ / IELTS 5.5",
    "focus": "Joining A New Team",
    "keywords": [
      "joining a new team",
      "全469节中英字幕【火爆油管外教英语】Vanessa English 覆盖语法+词汇+发音+学习方法四大板块 原汁原味学英语",
      "Vanessa English,英语学习方法,英语语法,外教,学习英语,英语学习,英语词汇,英语口语,外教英语,英语"
    ],
    "whySuitable": "Bilibili 可播放候选；如含外挂字幕，可直接生成逐句精听课程。",
    "transcriptSource": "unavailable",
    "transcriptSegments": [],
    "id": "ielts-5-5-32"
  },
  {
    "key": "BV1LheuzXEKr-2",
    "level": "IELTS 5.5",
    "topic": "Joining A New Team",
    "title": "全469节中英字幕【火爆油管外教英语】Vanessa English 覆盖语法+词汇+发音+学习方法四大板块 原汁原味学英语 - Vanessa-如何学习英语-02",
    "source": "Bilibili",
    "url": "https://www.bilibili.com/video/BV1LheuzXEKr?p=2",
    "embedUrl": "https://player.bilibili.com/player.html?bvid=BV1LheuzXEKr&page=2&autoplay=0",
    "bvid": "BV1LheuzXEKr",
    "cid": 31818383536,
    "page": 2,
    "playerType": "bilibili",
    "duration": "13:10",
    "durationSeconds": 790,
    "difficulty": "B1+ / IELTS 5.5",
    "focus": "Joining A New Team",
    "keywords": [
      "joining a new team",
      "全469节中英字幕【火爆油管外教英语】Vanessa English 覆盖语法+词汇+发音+学习方法四大板块 原汁原味学英语",
      "Vanessa English,英语学习方法,英语语法,外教,学习英语,英语学习,英语词汇,英语口语,外教英语,英语"
    ],
    "whySuitable": "Bilibili 可播放候选；如含外挂字幕，可直接生成逐句精听课程。",
    "transcriptSource": "unavailable",
    "transcriptSegments": [],
    "id": "ielts-5-5-33"
  },
  {
    "key": "BV1LheuzXEKr-3",
    "level": "IELTS 5.5",
    "topic": "Joining A New Team",
    "title": "全469节中英字幕【火爆油管外教英语】Vanessa English 覆盖语法+词汇+发音+学习方法四大板块 原汁原味学英语 - Vanessa-如何学习英语-03",
    "source": "Bilibili",
    "url": "https://www.bilibili.com/video/BV1LheuzXEKr?p=3",
    "embedUrl": "https://player.bilibili.com/player.html?bvid=BV1LheuzXEKr&page=3&autoplay=0",
    "bvid": "BV1LheuzXEKr",
    "cid": 31818383673,
    "page": 3,
    "playerType": "bilibili",
    "duration": "13:11",
    "durationSeconds": 791,
    "difficulty": "B1+ / IELTS 5.5",
    "focus": "Joining A New Team",
    "keywords": [
      "joining a new team",
      "全469节中英字幕【火爆油管外教英语】Vanessa English 覆盖语法+词汇+发音+学习方法四大板块 原汁原味学英语",
      "Vanessa English,英语学习方法,英语语法,外教,学习英语,英语学习,英语词汇,英语口语,外教英语,英语"
    ],
    "whySuitable": "Bilibili 可播放候选；如含外挂字幕，可直接生成逐句精听课程。",
    "transcriptSource": "unavailable",
    "transcriptSegments": [],
    "id": "ielts-5-5-34"
  },
  {
    "key": "BV1LheuzXEKr-5",
    "level": "IELTS 5.5",
    "topic": "Joining A New Team",
    "title": "全469节中英字幕【火爆油管外教英语】Vanessa English 覆盖语法+词汇+发音+学习方法四大板块 原汁原味学英语 - Vanessa-如何学习英语-05",
    "source": "Bilibili",
    "url": "https://www.bilibili.com/video/BV1LheuzXEKr?p=5",
    "embedUrl": "https://player.bilibili.com/player.html?bvid=BV1LheuzXEKr&page=5&autoplay=0",
    "bvid": "BV1LheuzXEKr",
    "cid": 31818384142,
    "page": 5,
    "playerType": "bilibili",
    "duration": "8:14",
    "durationSeconds": 494,
    "difficulty": "B1+ / IELTS 5.5",
    "focus": "Joining A New Team",
    "keywords": [
      "joining a new team",
      "全469节中英字幕【火爆油管外教英语】Vanessa English 覆盖语法+词汇+发音+学习方法四大板块 原汁原味学英语",
      "Vanessa English,英语学习方法,英语语法,外教,学习英语,英语学习,英语词汇,英语口语,外教英语,英语"
    ],
    "whySuitable": "Bilibili 可播放候选；如含外挂字幕，可直接生成逐句精听课程。",
    "transcriptSource": "unavailable",
    "transcriptSegments": [],
    "id": "ielts-5-5-35"
  },
  {
    "key": "BV1LheuzXEKr-6",
    "level": "IELTS 5.5",
    "topic": "Joining A New Team",
    "title": "全469节中英字幕【火爆油管外教英语】Vanessa English 覆盖语法+词汇+发音+学习方法四大板块 原汁原味学英语 - Vanessa-如何学习英语-06",
    "source": "Bilibili",
    "url": "https://www.bilibili.com/video/BV1LheuzXEKr?p=6",
    "embedUrl": "https://player.bilibili.com/player.html?bvid=BV1LheuzXEKr&page=6&autoplay=0",
    "bvid": "BV1LheuzXEKr",
    "cid": 31818384272,
    "page": 6,
    "playerType": "bilibili",
    "duration": "6:44",
    "durationSeconds": 404,
    "difficulty": "B1+ / IELTS 5.5",
    "focus": "Joining A New Team",
    "keywords": [
      "joining a new team",
      "全469节中英字幕【火爆油管外教英语】Vanessa English 覆盖语法+词汇+发音+学习方法四大板块 原汁原味学英语",
      "Vanessa English,英语学习方法,英语语法,外教,学习英语,英语学习,英语词汇,英语口语,外教英语,英语"
    ],
    "whySuitable": "Bilibili 可播放候选；如含外挂字幕，可直接生成逐句精听课程。",
    "transcriptSource": "unavailable",
    "transcriptSegments": [],
    "id": "ielts-5-5-36"
  },
  {
    "key": "BV1LheuzXEKr-7",
    "level": "IELTS 5.5",
    "topic": "Joining A New Team",
    "title": "全469节中英字幕【火爆油管外教英语】Vanessa English 覆盖语法+词汇+发音+学习方法四大板块 原汁原味学英语 - Vanessa-如何学习英语-07",
    "source": "Bilibili",
    "url": "https://www.bilibili.com/video/BV1LheuzXEKr?p=7",
    "embedUrl": "https://player.bilibili.com/player.html?bvid=BV1LheuzXEKr&page=7&autoplay=0",
    "bvid": "BV1LheuzXEKr",
    "cid": 31818384408,
    "page": 7,
    "playerType": "bilibili",
    "duration": "11:23",
    "durationSeconds": 683,
    "difficulty": "B1+ / IELTS 5.5",
    "focus": "Joining A New Team",
    "keywords": [
      "joining a new team",
      "全469节中英字幕【火爆油管外教英语】Vanessa English 覆盖语法+词汇+发音+学习方法四大板块 原汁原味学英语",
      "Vanessa English,英语学习方法,英语语法,外教,学习英语,英语学习,英语词汇,英语口语,外教英语,英语"
    ],
    "whySuitable": "Bilibili 可播放候选；如含外挂字幕，可直接生成逐句精听课程。",
    "transcriptSource": "unavailable",
    "transcriptSegments": [],
    "id": "ielts-5-5-37"
  },
  {
    "key": "BV1LheuzXEKr-9",
    "level": "IELTS 5.5",
    "topic": "Joining A New Team",
    "title": "全469节中英字幕【火爆油管外教英语】Vanessa English 覆盖语法+词汇+发音+学习方法四大板块 原汁原味学英语 - Vanessa-如何学习英语-09",
    "source": "Bilibili",
    "url": "https://www.bilibili.com/video/BV1LheuzXEKr?p=9",
    "embedUrl": "https://player.bilibili.com/player.html?bvid=BV1LheuzXEKr&page=9&autoplay=0",
    "bvid": "BV1LheuzXEKr",
    "cid": 31818384757,
    "page": 9,
    "playerType": "bilibili",
    "duration": "9:34",
    "durationSeconds": 574,
    "difficulty": "B1+ / IELTS 5.5",
    "focus": "Joining A New Team",
    "keywords": [
      "joining a new team",
      "全469节中英字幕【火爆油管外教英语】Vanessa English 覆盖语法+词汇+发音+学习方法四大板块 原汁原味学英语",
      "Vanessa English,英语学习方法,英语语法,外教,学习英语,英语学习,英语词汇,英语口语,外教英语,英语"
    ],
    "whySuitable": "Bilibili 可播放候选；如含外挂字幕，可直接生成逐句精听课程。",
    "transcriptSource": "unavailable",
    "transcriptSegments": [],
    "id": "ielts-5-5-38"
  },
  {
    "key": "BV1LheuzXEKr-10",
    "level": "IELTS 5.5",
    "topic": "Joining A New Team",
    "title": "全469节中英字幕【火爆油管外教英语】Vanessa English 覆盖语法+词汇+发音+学习方法四大板块 原汁原味学英语 - Vanessa-如何学习英语-10",
    "source": "Bilibili",
    "url": "https://www.bilibili.com/video/BV1LheuzXEKr?p=10",
    "embedUrl": "https://player.bilibili.com/player.html?bvid=BV1LheuzXEKr&page=10&autoplay=0",
    "bvid": "BV1LheuzXEKr",
    "cid": 31818385005,
    "page": 10,
    "playerType": "bilibili",
    "duration": "4:21",
    "durationSeconds": 261,
    "difficulty": "B1+ / IELTS 5.5",
    "focus": "Joining A New Team",
    "keywords": [
      "joining a new team",
      "全469节中英字幕【火爆油管外教英语】Vanessa English 覆盖语法+词汇+发音+学习方法四大板块 原汁原味学英语",
      "Vanessa English,英语学习方法,英语语法,外教,学习英语,英语学习,英语词汇,英语口语,外教英语,英语"
    ],
    "whySuitable": "Bilibili 可播放候选；如含外挂字幕，可直接生成逐句精听课程。",
    "transcriptSource": "unavailable",
    "transcriptSegments": [],
    "id": "ielts-5-5-39"
  },
  {
    "key": "BV1LheuzXEKr-11",
    "level": "IELTS 5.5",
    "topic": "Joining A New Team",
    "title": "全469节中英字幕【火爆油管外教英语】Vanessa English 覆盖语法+词汇+发音+学习方法四大板块 原汁原味学英语 - Vanessa-如何学习英语-11",
    "source": "Bilibili",
    "url": "https://www.bilibili.com/video/BV1LheuzXEKr?p=11",
    "embedUrl": "https://player.bilibili.com/player.html?bvid=BV1LheuzXEKr&page=11&autoplay=0",
    "bvid": "BV1LheuzXEKr",
    "cid": 31818384891,
    "page": 11,
    "playerType": "bilibili",
    "duration": "5:22",
    "durationSeconds": 322,
    "difficulty": "B1+ / IELTS 5.5",
    "focus": "Joining A New Team",
    "keywords": [
      "joining a new team",
      "全469节中英字幕【火爆油管外教英语】Vanessa English 覆盖语法+词汇+发音+学习方法四大板块 原汁原味学英语",
      "Vanessa English,英语学习方法,英语语法,外教,学习英语,英语学习,英语词汇,英语口语,外教英语,英语"
    ],
    "whySuitable": "Bilibili 可播放候选；如含外挂字幕，可直接生成逐句精听课程。",
    "transcriptSource": "unavailable",
    "transcriptSegments": [],
    "id": "ielts-5-5-40"
  },
  {
    "key": "BV1LheuzXEKr-12",
    "level": "IELTS 5.5",
    "topic": "Joining A New Team",
    "title": "全469节中英字幕【火爆油管外教英语】Vanessa English 覆盖语法+词汇+发音+学习方法四大板块 原汁原味学英语 - Vanessa-如何学习英语-12",
    "source": "Bilibili",
    "url": "https://www.bilibili.com/video/BV1LheuzXEKr?p=12",
    "embedUrl": "https://player.bilibili.com/player.html?bvid=BV1LheuzXEKr&page=12&autoplay=0",
    "bvid": "BV1LheuzXEKr",
    "cid": 31818384984,
    "page": 12,
    "playerType": "bilibili",
    "duration": "4:55",
    "durationSeconds": 295,
    "difficulty": "B1+ / IELTS 5.5",
    "focus": "Joining A New Team",
    "keywords": [
      "joining a new team",
      "全469节中英字幕【火爆油管外教英语】Vanessa English 覆盖语法+词汇+发音+学习方法四大板块 原汁原味学英语",
      "Vanessa English,英语学习方法,英语语法,外教,学习英语,英语学习,英语词汇,英语口语,外教英语,英语"
    ],
    "whySuitable": "Bilibili 可播放候选；如含外挂字幕，可直接生成逐句精听课程。",
    "transcriptSource": "unavailable",
    "transcriptSegments": [],
    "id": "ielts-5-5-41"
  },
  {
    "key": "BV1qbC6YtE91-2",
    "level": "IELTS 5.5",
    "topic": "Joining A New Team",
    "title": "【全1073集 】English Singsing 英语启蒙必看-零基础儿童词汇 适合2-8岁小朋友的英语学习教材 【英语 英文字幕】 - 02. Kids Vocabulary - Animal Sounds - Various Animal Sounds- Learn English for k",
    "source": "Bilibili",
    "url": "https://www.bilibili.com/video/BV1qbC6YtE91?p=2",
    "embedUrl": "https://player.bilibili.com/player.html?bvid=BV1qbC6YtE91&page=2&autoplay=0",
    "bvid": "BV1qbC6YtE91",
    "cid": 27539472424,
    "page": 2,
    "playerType": "bilibili",
    "duration": "6:28",
    "durationSeconds": 388,
    "difficulty": "B1+ / IELTS 5.5",
    "focus": "Joining A New Team",
    "keywords": [
      "joining a new team",
      "【全1073集 】English Singsing 英语启蒙必看-零基础儿童词汇 适合2-8岁小朋友的英语学习教材 【英语 英文字幕】",
      "英语学习,英语启蒙,英语早教,English Singsing,零基础,英语词汇,英语口语,英语听力,少儿英语,磨耳朵"
    ],
    "whySuitable": "Bilibili 可播放候选；如含外挂字幕，可直接生成逐句精听课程。",
    "transcriptSource": "unavailable",
    "transcriptSegments": [],
    "id": "ielts-5-5-42"
  },
  {
    "key": "BV1qbC6YtE91-3",
    "level": "IELTS 5.5",
    "topic": "Joining A New Team",
    "title": "【全1073集 】English Singsing 英语启蒙必看-零基础儿童词汇 适合2-8岁小朋友的英语学习教材 【英语 英文字幕】 - 03. Kids vocabulary - [Old] Action Verbs - Action Words - Learn English for kids",
    "source": "Bilibili",
    "url": "https://www.bilibili.com/video/BV1qbC6YtE91?p=3",
    "embedUrl": "https://player.bilibili.com/player.html?bvid=BV1qbC6YtE91&page=3&autoplay=0",
    "bvid": "BV1qbC6YtE91",
    "cid": 27539472606,
    "page": 3,
    "playerType": "bilibili",
    "duration": "4:23",
    "durationSeconds": 263,
    "difficulty": "B1+ / IELTS 5.5",
    "focus": "Joining A New Team",
    "keywords": [
      "joining a new team",
      "【全1073集 】English Singsing 英语启蒙必看-零基础儿童词汇 适合2-8岁小朋友的英语学习教材 【英语 英文字幕】",
      "英语学习,英语启蒙,英语早教,English Singsing,零基础,英语词汇,英语口语,英语听力,少儿英语,磨耳朵"
    ],
    "whySuitable": "Bilibili 可播放候选；如含外挂字幕，可直接生成逐句精听课程。",
    "transcriptSource": "unavailable",
    "transcriptSegments": [],
    "id": "ielts-5-5-43"
  },
  {
    "key": "BV1qbC6YtE91-4",
    "level": "IELTS 5.5",
    "topic": "Joining A New Team",
    "title": "【全1073集 】English Singsing 英语启蒙必看-零基础儿童词汇 适合2-8岁小朋友的英语学习教材 【英语 英文字幕】 - 04. Kids vocabulary - [Old] Opposite Words - Learning about Opposites - English",
    "source": "Bilibili",
    "url": "https://www.bilibili.com/video/BV1qbC6YtE91?p=4",
    "embedUrl": "https://player.bilibili.com/player.html?bvid=BV1qbC6YtE91&page=4&autoplay=0",
    "bvid": "BV1qbC6YtE91",
    "cid": 27539472530,
    "page": 4,
    "playerType": "bilibili",
    "duration": "6:16",
    "durationSeconds": 376,
    "difficulty": "B1+ / IELTS 5.5",
    "focus": "Joining A New Team",
    "keywords": [
      "joining a new team",
      "【全1073集 】English Singsing 英语启蒙必看-零基础儿童词汇 适合2-8岁小朋友的英语学习教材 【英语 英文字幕】",
      "英语学习,英语启蒙,英语早教,English Singsing,零基础,英语词汇,英语口语,英语听力,少儿英语,磨耳朵"
    ],
    "whySuitable": "Bilibili 可播放候选；如含外挂字幕，可直接生成逐句精听课程。",
    "transcriptSource": "unavailable",
    "transcriptSegments": [],
    "id": "ielts-5-5-44"
  },
  {
    "key": "BV1qbC6YtE91-5",
    "level": "IELTS 5.5",
    "topic": "Joining A New Team",
    "title": "【全1073集 】English Singsing 英语启蒙必看-零基础儿童词汇 适合2-8岁小朋友的英语学习教材 【英语 英文字幕】 - 05. Kids vocabulary - Human Sounds - imitating sounds - English educational vide",
    "source": "Bilibili",
    "url": "https://www.bilibili.com/video/BV1qbC6YtE91?p=5",
    "embedUrl": "https://player.bilibili.com/player.html?bvid=BV1qbC6YtE91&page=5&autoplay=0",
    "bvid": "BV1qbC6YtE91",
    "cid": 27539472531,
    "page": 5,
    "playerType": "bilibili",
    "duration": "4:11",
    "durationSeconds": 251,
    "difficulty": "B1+ / IELTS 5.5",
    "focus": "Joining A New Team",
    "keywords": [
      "joining a new team",
      "【全1073集 】English Singsing 英语启蒙必看-零基础儿童词汇 适合2-8岁小朋友的英语学习教材 【英语 英文字幕】",
      "英语学习,英语启蒙,英语早教,English Singsing,零基础,英语词汇,英语口语,英语听力,少儿英语,磨耳朵"
    ],
    "whySuitable": "Bilibili 可播放候选；如含外挂字幕，可直接生成逐句精听课程。",
    "transcriptSource": "unavailable",
    "transcriptSegments": [],
    "id": "ielts-5-5-45"
  },
  {
    "key": "BV1qbC6YtE91-8",
    "level": "IELTS 5.5",
    "topic": "Joining A New Team",
    "title": "【全1073集 】English Singsing 英语启蒙必看-零基础儿童词汇 适合2-8岁小朋友的英语学习教材 【英语 英文字幕】 - 08. Kids vocabulary - Shape - Names of Shapes - Learn English for kids - English",
    "source": "Bilibili",
    "url": "https://www.bilibili.com/video/BV1qbC6YtE91?p=8",
    "embedUrl": "https://player.bilibili.com/player.html?bvid=BV1qbC6YtE91&page=8&autoplay=0",
    "bvid": "BV1qbC6YtE91",
    "cid": 27539472912,
    "page": 8,
    "playerType": "bilibili",
    "duration": "5:28",
    "durationSeconds": 328,
    "difficulty": "B1+ / IELTS 5.5",
    "focus": "Joining A New Team",
    "keywords": [
      "joining a new team",
      "【全1073集 】English Singsing 英语启蒙必看-零基础儿童词汇 适合2-8岁小朋友的英语学习教材 【英语 英文字幕】",
      "英语学习,英语启蒙,英语早教,English Singsing,零基础,英语词汇,英语口语,英语听力,少儿英语,磨耳朵"
    ],
    "whySuitable": "Bilibili 可播放候选；如含外挂字幕，可直接生成逐句精听课程。",
    "transcriptSource": "unavailable",
    "transcriptSegments": [],
    "id": "ielts-5-5-46"
  },
  {
    "key": "BV1qbC6YtE91-10",
    "level": "IELTS 5.5",
    "topic": "Joining A New Team",
    "title": "【全1073集 】English Singsing 英语启蒙必看-零基础儿童词汇 适合2-8岁小朋友的英语学习教材 【英语 英文字幕】 - 10. Kids vocabulary - Olympic Sports - Game of Sports - Learn English for kids -",
    "source": "Bilibili",
    "url": "https://www.bilibili.com/video/BV1qbC6YtE91?p=10",
    "embedUrl": "https://player.bilibili.com/player.html?bvid=BV1qbC6YtE91&page=10&autoplay=0",
    "bvid": "BV1qbC6YtE91",
    "cid": 27539472743,
    "page": 10,
    "playerType": "bilibili",
    "duration": "6:51",
    "durationSeconds": 411,
    "difficulty": "B1+ / IELTS 5.5",
    "focus": "Joining A New Team",
    "keywords": [
      "joining a new team",
      "【全1073集 】English Singsing 英语启蒙必看-零基础儿童词汇 适合2-8岁小朋友的英语学习教材 【英语 英文字幕】",
      "英语学习,英语启蒙,英语早教,English Singsing,零基础,英语词汇,英语口语,英语听力,少儿英语,磨耳朵"
    ],
    "whySuitable": "Bilibili 可播放候选；如含外挂字幕，可直接生成逐句精听课程。",
    "transcriptSource": "unavailable",
    "transcriptSegments": [],
    "id": "ielts-5-5-47"
  },
  {
    "key": "BV1qbC6YtE91-12",
    "level": "IELTS 5.5",
    "topic": "Joining A New Team",
    "title": "【全1073集 】English Singsing 英语启蒙必看-零基础儿童词汇 适合2-8岁小朋友的英语学习教材 【英语 英文字幕】 - 12. Kids vocabulary - Color - color mixing - rainbow colors - English educationa",
    "source": "Bilibili",
    "url": "https://www.bilibili.com/video/BV1qbC6YtE91?p=12",
    "embedUrl": "https://player.bilibili.com/player.html?bvid=BV1qbC6YtE91&page=12&autoplay=0",
    "bvid": "BV1qbC6YtE91",
    "cid": 27539472852,
    "page": 12,
    "playerType": "bilibili",
    "duration": "4:40",
    "durationSeconds": 280,
    "difficulty": "B1+ / IELTS 5.5",
    "focus": "Joining A New Team",
    "keywords": [
      "joining a new team",
      "【全1073集 】English Singsing 英语启蒙必看-零基础儿童词汇 适合2-8岁小朋友的英语学习教材 【英语 英文字幕】",
      "英语学习,英语启蒙,英语早教,English Singsing,零基础,英语词汇,英语口语,英语听力,少儿英语,磨耳朵"
    ],
    "whySuitable": "Bilibili 可播放候选；如含外挂字幕，可直接生成逐句精听课程。",
    "transcriptSource": "unavailable",
    "transcriptSegments": [],
    "id": "ielts-5-5-48"
  },
  {
    "key": "BV1qbC6YtE91-13",
    "level": "IELTS 5.5",
    "topic": "Joining A New Team",
    "title": "【全1073集 】English Singsing 英语启蒙必看-零基础儿童词汇 适合2-8岁小朋友的英语学习教材 【英语 英文字幕】 - 13. Kids vocabulary -[Old] Fruits & Vegetables - Learn English for kids - Englis",
    "source": "Bilibili",
    "url": "https://www.bilibili.com/video/BV1qbC6YtE91?p=13",
    "embedUrl": "https://player.bilibili.com/player.html?bvid=BV1qbC6YtE91&page=13&autoplay=0",
    "bvid": "BV1qbC6YtE91",
    "cid": 27539472850,
    "page": 13,
    "playerType": "bilibili",
    "duration": "4:28",
    "durationSeconds": 268,
    "difficulty": "B1+ / IELTS 5.5",
    "focus": "Joining A New Team",
    "keywords": [
      "joining a new team",
      "【全1073集 】English Singsing 英语启蒙必看-零基础儿童词汇 适合2-8岁小朋友的英语学习教材 【英语 英文字幕】",
      "英语学习,英语启蒙,英语早教,English Singsing,零基础,英语词汇,英语口语,英语听力,少儿英语,磨耳朵"
    ],
    "whySuitable": "Bilibili 可播放候选；如含外挂字幕，可直接生成逐句精听课程。",
    "transcriptSource": "unavailable",
    "transcriptSegments": [],
    "id": "ielts-5-5-49"
  },
  {
    "key": "BV1qbC6YtE91-15",
    "level": "IELTS 5.5",
    "topic": "Joining A New Team",
    "title": "【全1073集 】English Singsing 英语启蒙必看-零基础儿童词汇 适合2-8岁小朋友的英语学习教材 【英语 英文字幕】 - 15. Kids vocabulary - [Old] Jobs - Let's learn about jobs - Learn English for ki",
    "source": "Bilibili",
    "url": "https://www.bilibili.com/video/BV1qbC6YtE91?p=15",
    "embedUrl": "https://player.bilibili.com/player.html?bvid=BV1qbC6YtE91&page=15&autoplay=0",
    "bvid": "BV1qbC6YtE91",
    "cid": 27539473217,
    "page": 15,
    "playerType": "bilibili",
    "duration": "6:46",
    "durationSeconds": 406,
    "difficulty": "B1+ / IELTS 5.5",
    "focus": "Joining A New Team",
    "keywords": [
      "joining a new team",
      "【全1073集 】English Singsing 英语启蒙必看-零基础儿童词汇 适合2-8岁小朋友的英语学习教材 【英语 英文字幕】",
      "英语学习,英语启蒙,英语早教,English Singsing,零基础,英语词汇,英语口语,英语听力,少儿英语,磨耳朵"
    ],
    "whySuitable": "Bilibili 可播放候选；如含外挂字幕，可直接生成逐句精听课程。",
    "transcriptSource": "unavailable",
    "transcriptSegments": [],
    "id": "ielts-5-5-50"
  }
]
